tmdbone/__init__.py
tmdbone/client.py
tmdbone/exceptions.py
tmdbone/resources.py
tmdbone-1.0.0.dist-info/METADATA
tmdbone-1.0.0.dist-info/WHEEL
tmdbone-1.0.0.dist-info/licenses/LICENSE
tmdbone-1.0.0.dist-info/RECORD
