Metadata-Version: 2.4
Name: tmdbone
Version: 1.0.0
Summary: A resilient and comprehensive asynchronous TMDb API library with key rotation.
Project-URL: Homepage, https://github.com/onthejobtraining/tmdbone
Project-URL: Bug Tracker, https://github.com/onthejobtraining/tmdbone/issues
Author: onthejobtraining
License: MIT License
License-File: LICENSE
Keywords: api,asyncio,movie,resilient,tmdb,tv,wrapper
Classifier: Development Status :: 5 - Production/Stable
Classifier: Framework :: AsyncIO
Classifier: Intended Audience :: Developers
Classifier: License :: OSI Approved :: MIT License
Classifier: Operating System :: OS Independent
Classifier: Programming Language :: Python :: 3
Classifier: Topic :: Internet :: WWW/HTTP
Classifier: Topic :: Software Development :: Libraries :: Python Modules
Requires-Python: >=3.7
Requires-Dist: aiohttp>=3.8.0
